[
  {
    "nama": "Mr. Imam Bardjo",
    "periode": "1957",
    "keterangan": "Rektor/presiden Universitas Semarang (cikal bakal Undip); rektor pertama sejak pembukaan 9 Jan 1957.",
    "sumber": "Wikipedia"
  },
  {
    "nama": "Prof. (Ir.) Jacub / Jakub (Jacob) Rais",
    "periode": "Okt 1965 – Des 1966",
    "keterangan": "Tercatat pernah menjabat caretaker rektor dalam periode singkat.",
    "sumber": "Wikipedia"
  },
  {
    "nama": "Prof. Soedarto",
    "periode": "Tidak diketahui pasti",
    "keterangan": "Tercatat pernah menjabat; nama muncul dalam sejarah pimpinan Undip.",
    "sumber": "Wikipedia"
  },
  {
    "nama": "Prof. dr. Moeljono S. Trastotenojo",
    "periode": "Awal 1990-an",
    "keterangan": "Disebut sebagai rektor pada awal 1990-an dalam catatan pengembangan fakultas.",
    "sumber": "Universitas STEKOM Semarang"
  },
  {
    "nama": "Prof. Muladi",
    "periode": "1994–1998",
    "keterangan": "Menjabat sebagai Rektor Undip, disebut dalam liputan berita.",
    "sumber": "Antara News Jawa Timur"
  },
  {
    "nama": "Prof. Sudharto P. Hadi",
    "periode": "Tidak diketahui pasti",
    "keterangan": "Tercantum dalam dokumen Universitas/renstra sebagai bagian kepemimpinan Undip.",
    "sumber": "ndanimations.fr"
  },
  {
    "nama": "Prof. Dr. Yos Johan Utama, S.H., M.Hum.",
    "periode": "2015–2019, 2019–2024",
    "keterangan": "Rektor Undip dua periode berturut-turut.",
    "sumber": "alumniprofile.undip.ac.id"
  },
  {
    "nama": "Prof. Dr. Suharnomo, S.E., M.Si.",
    "periode": "2024–2029",
    "keterangan": "Rektor Undip periode 2024–2029 (sekarang).",
    "sumber": "Rektor Undip"
  }
]
